{
  "filename": "NE01413.pdf",
  "path": "PRODAM_DOCS\\DETRAN_CONSOLIDADO\\02_EMPENHOS\\NE01413.pdf",
  "categoria": "02_EMPENHOS",
  "data_extracao": "2026-04-14",
  "tamanho_bytes": 1314751,
  "texto_length": 2910,
  "texto_preview": "W.—( GOVERNO DE ESTADO DO AMAZONAS ADMINISTRAÇÃO FINANCEIRA INTEGRADA\n\nNota de Empenho\n\nUnidade Gestora Número Documento\n022201 - DEPARTAMENTO ESTADUAL DE TRÂNSITO 2014NE01413\n\nNE Original\n(DOQZ AUTARQUIA &22201 WIMQIZON\n\nCmdof\n04407920000180 - PRODAM FROCESSALÉNTO DE DADOS AMAZONAS SA\n\n06.122.0001 .2001.000t\n04010000\n33903908\n\nUnid. Descrição Qtde —PreçoUnitário Preço Total\nSERVIÇO 110541 - (10-110541) SERVIÇOS DE PROCESSAMENTO DE DADOS, Descrição Contratação de empress 1 78,000.4600 78.000,46\nespecializada na prestação de serviços de acesso à Rede de Governo, com o fornecimento de link seguro.\nformando uma rede uúnica do ORGÃO SOLICITANTE para acesso gerenciado aos sistemas contratados e\nhospedados na PRODAM. residentes no Data Center do Estado, conforme Projeto Básico MARCA: sem marca\n\n",
  "texto_completo": "W.—( GOVERNO DE ESTADO DO AMAZONAS ADMINISTRAÇÃO FINANCEIRA INTEGRADA\n\nNota de Empenho\n\nUnidade Gestora Número Documento\n022201 - DEPARTAMENTO ESTADUAL DE TRÂNSITO 2014NE01413\n\nNE Original\n(DOQZ AUTARQUIA &22201 WIMQIZON\n\nCmdof\n04407920000180 - PRODAM FROCESSALÉNTO DE DADOS AMAZONAS SA\n\n06.122.0001 .2001.000t\n04010000\n33903908\n\nUnid. Descrição Qtde —PreçoUnitário Preço Total\nSERVIÇO 110541 - (10-110541) SERVIÇOS DE PROCESSAMENTO DE DADOS, Descrição Contratação de empress 1 78,000.4600 78.000,46\nespecializada na prestação de serviços de acesso à Rede de Governo, com o fornecimento de link seguro.\nformando uma rede uúnica do ORGÃO SOLICITANTE para acesso gerenciado aos sistemas contratados e\nhospedados na PRODAM. residentes no Data Center do Estado, conforme Projeto Básico MARCA: sem marca\n\nPARECER TECNICO CEPINF Nº3312/2014/SEPLAN\nDESRIÇÃO DOS SERVIÇOS:\n\nANEXO 01-PRESTAÇÃO DE SERVIÇOS TECNICOS EM TELECOMUNICAÇÕES DISPONIBILIZANDO ACESSO\nÀ INTERNET (REDE DO GOVERNO) AO COMPUTADOR CENTRAL DA PRODAM, E SERVIÇO FASTNET DA\nEMBRATEL.\n\nFUNDAMNENTO LEGAL: DISPENSA DE LICITAÇÃO ART.24 XV LEI Nº6.666/83\nPORTARIA Nº3126/201 /DE TRAN/AM/AJUR. PUBLICADA D.O.E. DE 25/11/2014 Nº32.932\nRDt Nº024/2014-e-compras\n\nCONTRATO A SER FIRMADO\n\nVIGENCIA. 12 MESES CONTADOS A PARTIR DA DATA DA ASSINATURA\n\nVALOR GLOBAL ESTIMADO: R$ 468.002.76\n\nVALOR MENSAL ESTIMADO: R$ 39.000 23 (02 MESES NOVIDEZ/2014)\n\nVALOR À SER EMPENHADO NO PROXIMO EXERCICIO: R$ 380.002.30 ( 19 MESES)\n\nPARECER Nº1504/2014-ASS/CGt.\nPROCESSO Nº013.46043/2014/CGL. OFICIO Nº8470/2014-GP/CGL\nPROCESSO Nº1349/2014/DE TRAN/AM\n\n78.000,46 i 41498419\n\nDETRANIAM\nSUELI DE CASTRO JOHNSON\n\nReiNes rpt\n\n\n===PAGINA===\n\nGOVERNO DE ESTADO DO AMAZONAS ADMINISTRAÇÃO FINANCEIRA INTEGRADA\n\nNota de Empenho\n\nUnidade Gestora Número Documento\n022201 - DEPARTAMENTO ESTADUAL DE TRÂNSITO 2014NE01413\n\nProcesso\n00002 - AUTARQUIA 022201.001349/2014\n\nLicitação\n04407920000180 - PRODAM PROCESSAMENTO DE DADOS AMAZONAS SA 5 - Dispensa de Licitação\n\nCertificados:\n\nCertificados\n\n* CERTIDÃO NEGATIVA DA FAZENDA FEDERAL (2360 EDF86.A197.9C48) - Início 06/10/2014 - Venc 06/04/2015\n\n* CERTIDÃO NEGATIVA DA FAZENDA ESTADUAL (16732978) - Início 25/1 1/2014 - Venc 25/12/2014\n\n* CERTIDÃO NEGATIVA DA FAZENDA MUNICIPAL (115785/2014) - iníco 18/1 112014 - Venc. 16/02/2015\n\nCERTIDÃO NEGATIVA DA PROCURADORIA DA FAZENDA NACIONAL - DIVIDA ATIVA (2360 .EDF6.A197.9C48) - Início 08/10/2014 - Venc 06/04/2015\nERTIDÃO NEGATIVA DO FGTS (2014110304154620562806) - início 03/11/2014 - Venc. 02/12/2014\n\n* CERTIDÃO NEGATIVA DO INSS (199312014-8888920) - Início 10/07/2014 - Venc. 06/01/22015\n\n* CERTIDÃO NEGATIVA DE DÉBITOS TRABALHISTAS (65130329/2014) - Início 14/10/2014 - Venc: 11/04/2018\n\n492.984 65 Valor do Empenho: 78.000,46 Valor Disponível 414984 19\n\n27112015\nDeperaneno Fs da Thccin À | de Entrega: DETRAN/AM\nDegeranentoEsatia d Tin do lan Operador da NE : SUELI DE CASTRO JORNSON\n\n",
  "pdf_meta": {
    "metodo": "ocr_tesseract_fase2",
    "paginas": 2,
    "tem_texto": false,
    "paginas_ocr": 2,
    "tempo_ocr_s": 4.7
  },
  "precisa_ocr": false,
  "campos_estruturados": {
    "tipo_doc": "NOTA_EMPENHO",
    "datas_encontradas": [
      "25/11/2014",
      "06/10/2014",
      "06/04/2015",
      "25/12/2014",
      "16/02/2015",
      "08/10/2014",
      "03/11/2014",
      "02/12/2014",
      "10/07/2014",
      "14/10/2014"
    ],
    "valores_brl": [
      "468.002.76",
      "39.000",
      "380.002.30"
    ],
    "nes_referenciadas": [
      "2014NE01413"
    ]
  },
  "ocr_texto": "W.—( GOVERNO DE ESTADO DO AMAZONAS ADMINISTRAÇÃO FINANCEIRA INTEGRADA\n\nNota de Empenho\n\nUnidade Gestora Número Documento\n022201 - DEPARTAMENTO ESTADUAL DE TRÂNSITO 2014NE01413\n\nNE Original\n(DOQZ AUTARQUIA &22201 WIMQIZON\n\nCmdof\n04407920000180 - PRODAM FROCESSALÉNTO DE DADOS AMAZONAS SA\n\n06.122.0001 .2001.000t\n04010000\n33903908\n\nUnid. Descrição Qtde —PreçoUnitário Preço Total\nSERVIÇO 110541 - (10-110541) SERVIÇOS DE PROCESSAMENTO DE DADOS, Descrição Contratação de empress 1 78,000.4600 78.000,46\nespecializada na prestação de serviços de acesso à Rede de Governo, com o fornecimento de link seguro.\nformando uma rede uúnica do ORGÃO SOLICITANTE para acesso gerenciado aos sistemas contratados e\nhospedados na PRODAM. residentes no Data Center do Estado, conforme Projeto Básico MARCA: sem marca\n\nPARECER TECNICO CEPINF Nº3312/2014/SEPLAN\nDESRIÇÃO DOS SERVIÇOS:\n\nANEXO 01-PRESTAÇÃO DE SERVIÇOS TECNICOS EM TELECOMUNICAÇÕES DISPONIBILIZANDO ACESSO\nÀ INTERNET (REDE DO GOVERNO) AO COMPUTADOR CENTRAL DA PRODAM, E SERVIÇO FASTNET DA\nEMBRATEL.\n\nFUNDAMNENTO LEGAL: DISPENSA DE LICITAÇÃO ART.24 XV LEI Nº6.666/83\nPORTARIA Nº3126/201 /DE TRAN/AM/AJUR. PUBLICADA D.O.E. DE 25/11/2014 Nº32.932\nRDt Nº024/2014-e-compras\n\nCONTRATO A SER FIRMADO\n\nVIGENCIA. 12 MESES CONTADOS A PARTIR DA DATA DA ASSINATURA\n\nVALOR GLOBAL ESTIMADO: R$ 468.002.76\n\nVALOR MENSAL ESTIMADO: R$ 39.000 23 (02 MESES NOVIDEZ/2014)\n\nVALOR À SER EMPENHADO NO PROXIMO EXERCICIO: R$ 380.002.30 ( 19 MESES)\n\nPARECER Nº1504/2014-ASS/CGt.\nPROCESSO Nº013.46043/2014/CGL. OFICIO Nº8470/2014-GP/CGL\nPROCESSO Nº1349/2014/DE TRAN/AM\n\n78.000,46 i 41498419\n\nDETRANIAM\nSUELI DE CASTRO JOHNSON\n\nReiNes rpt\n\n\n===PAGINA===\n\nGOVERNO DE ESTADO DO AMAZONAS ADMINISTRAÇÃO FINANCEIRA INTEGRADA\n\nNota de Empenho\n\nUnidade Gestora Número Documento\n022201 - DEPARTAMENTO ESTADUAL DE TRÂNSITO 2014NE01413\n\nProcesso\n00002 - AUTARQUIA 022201.001349/2014\n\nLicitação\n04407920000180 - PRODAM PROCESSAMENTO DE DADOS AMAZONAS SA 5 - Dispensa de Licitação\n\nCertificados:\n\nCertificados\n\n* CERTIDÃO NEGATIVA DA FAZENDA FEDERAL (2360 EDF86.A197.9C48) - Início 06/10/2014 - Venc 06/04/2015\n\n* CERTIDÃO NEGATIVA DA FAZENDA ESTADUAL (16732978) - Início 25/1 1/2014 - Venc 25/12/2014\n\n* CERTIDÃO NEGATIVA DA FAZENDA MUNICIPAL (115785/2014) - iníco 18/1 112014 - Venc. 16/02/2015\n\nCERTIDÃO NEGATIVA DA PROCURADORIA DA FAZENDA NACIONAL - DIVIDA ATIVA (2360 .EDF6.A197.9C48) - Início 08/10/2014 - Venc 06/04/2015\nERTIDÃO NEGATIVA DO FGTS (2014110304154620562806) - início 03/11/2014 - Venc. 02/12/2014\n\n* CERTIDÃO NEGATIVA DO INSS (199312014-8888920) - Início 10/07/2014 - Venc. 06/01/22015\n\n* CERTIDÃO NEGATIVA DE DÉBITOS TRABALHISTAS (65130329/2014) - Início 14/10/2014 - Venc: 11/04/2018\n\n492.984 65 Valor do Empenho: 78.000,46 Valor Disponível 414984 19\n\n27112015\nDeperaneno Fs da Thccin À | de Entrega: DETRAN/AM\nDegeranentoEsatia d Tin do lan Operador da NE : SUELI DE CASTRO JORNSON\n\n"
}